Metadata-Version: 1.2
Name: aio-mqtt
Version: 0.2.0
Summary: Asynchronous MQTT client for 3.1.1 protocol version.
Home-page: https://github.com/NotJustAToy/aio-mqtt
Author: Not Just A Toy Corp.
Author-email: dev@notjustatoy.com
License: Apache License 2.0
Keywords: mqtt asyncio
Platform: UNKNOWN
Classifier: Development Status :: 4 - Beta
Classifier: Intended Audience :: Developers
Classifier: License :: OSI Approved :: Apache Software License
Classifier: Operating System :: MacOS :: MacOS X
Classifier: Operating System :: Microsoft :: Windows
Classifier: Operating System :: POSIX
Classifier: Natural Language :: English
Classifier: Programming Language :: Python
Classifier: Programming Language :: Python :: 3
Classifier: Programming Language :: Python :: 3.6
Classifier: Programming Language :: Python :: 3.7
Classifier: Programming Language :: Python :: 3.8
Classifier: Topic :: Communications
Classifier: Topic :: Internet
Requires-Python: >=3.6.0
